{
  "project_info": {
    "project_number": "232472544702",
    "project_id": "icuisine-41831",
    "storage_bucket": "icuisine-41831.firebasestorage.app"
  },
  "client": [
    {
      "client_info": {
        "mobilesdk_app_id": "1:232472544702:android:e02efef291c1615f2365ef",
        "android_client_info": {
          "package_name": "com.example.icuisine"
        }
      },
      "oauth_client": [],
      "api_key": [
        {
          "current_key": "AIzaSyDQx2CQX1Y-lcLxk18aPfU-qlFuCDkvh-8"
        }
      ],
      "services": {
        "appinvite_service": {
          "other_platform_oauth_client": []
        }
      }
    }
  ],
  "configuration_version": "1"
}